directory_organizer.py
extensionsDirectory.py
oopsImplementation.py
directory_organizer-1.0.5.dist-info/LICENSE.md
directory_organizer-1.0.5.dist-info/METADATA
directory_organizer-1.0.5.dist-info/WHEEL
directory_organizer-1.0.5.dist-info/top_level.txt
directory_organizer-1.0.5.dist-info/RECORD
