Metadata-Version: 2.1
Name: directory-organizer
Version: 1.0.5
Summary: Utility Package that organizes and moves the specific file types to its type Specific Directories
Home-page: https://github.com/rahulbordoloi/Directory-Organizer/
Author: Rahul Bordoloi
Author-email: rahulbordoloi24@gmail.com
Maintainer: Sourav Mazumdar
Maintainer-email: souravmzdr@gmail.com
License: UNKNOWN
Platform: UNKNOWN
Classifier: Programming Language :: Python :: 3
Classifier: Programming Language :: Python :: 3.6
Classifier: Programming Language :: Python :: 3.7
Classifier: Programming Language :: Python :: 3.8
Classifier: Operating System :: OS Independent
Classifier: License :: OSI Approved :: GNU General Public License v3 (GPLv3)
Classifier: Topic :: Utilities
Classifier: Natural Language :: English
Classifier: Development Status :: 5 - Production/Stable
Classifier: Intended Audience :: Customer Service
Classifier: Intended Audience :: Developers
Classifier: Intended Audience :: End Users/Desktop
Provides-Extra: dev
Requires-Dist: pytest (>=3.7) ; extra == 'dev'
